compose.py
compose_func-1.0.1.dist-info/DESCRIPTION.rst
compose_func-1.0.1.dist-info/METADATA
compose_func-1.0.1.dist-info/RECORD
compose_func-1.0.1.dist-info/WHEEL
compose_func-1.0.1.dist-info/metadata.json
compose_func-1.0.1.dist-info/top_level.txt
