Metadata-Version: 2.0
Name: compose-func
Version: 1.0.1
Summary: No frills function composition
Home-page: https://github.com/jonathanj/compose
Author: Jonathan Jacobs
Author-email: jonathan@jsphere.com
License: MIT
Platform: any
Classifier: Development Status :: 5 - Production/Stable
Classifier: Topic :: Software Development :: Libraries
Classifier: Intended Audience :: Developers
Classifier: License :: OSI Approved :: MIT License
Classifier: Operating System :: OS Independent
Classifier: Programming Language :: Python
